pubmed_fetcher/__init__.py
pubmed_fetcher/main.py
pubmed_paper_fetcher_sharanya-0.1.0.dist-info/entry_points.txt
pubmed_paper_fetcher_sharanya-0.1.0.dist-info/METADATA
pubmed_paper_fetcher_sharanya-0.1.0.dist-info/WHEEL
pubmed_paper_fetcher_sharanya-0.1.0.dist-info/RECORD
