Metadata-Version: 2.3
Name: pubmed-paper-fetcher-sharanya
Version: 0.1.0
Summary: Fetch research papers from PubMed with company affiliations.
Author: Naga Sharanya kashanagasharanya@gmail.com
Requires-Python: >=3.11,<4.0
Classifier: Programming Language :: Python :: 3
Classifier: Programming Language :: Python :: 3.11
Classifier: Programming Language :: Python :: 3.12
Classifier: Programming Language :: Python :: 3.13
Requires-Dist: lxml (>=5.3.1,<6.0.0)
Requires-Dist: pandas (>=2.2.3,<3.0.0)
Requires-Dist: requests (>=2.32.3,<3.0.0)
